{
    "needsErrorInfo": false,
    "mobileBottomRow": 8,
    "widgetName": "Text1",
    "displayName": "Text",
    "iconSVG": "/static/media/icon.a47d6d5dbbb718c4dc4b2eb4f218c1b7.svg",
    "searchTags": [
        "typography",
        "paragraph",
        "label"
    ],
    "topRow": 1,
    "bottomRow": 14,
    "parentRowSpace": 10,
    "type": "TEXT_WIDGET",
    "hideCard": false,
    "mobileRightColumn": 40,
    "animateLoading": true,
    "overflow": "NONE",
    "fontFamily": "Montserrat",
    "parentColumnSpace": 12.9111328125,
    "dynamicTriggerPathList": [],
    "leftColumn": 21,
    "dynamicBindingPathList": [
        {"key": "truncateButtonColor"},
        {"key": "borderRadius"}
    ],
    "shouldTruncate": false,
    "truncateButtonColor": "{{appsmith.theme.colors.primaryColor}}",
    "text": "Edit Restaurant",
    "key": "y19mvlbots",
    "isDeprecated": false,
    "rightColumn": 44,
    "textAlign": "CENTER",
    "dynamicHeight": "AUTO_HEIGHT",
    "widgetId": "2262g4he11",
    "minWidth": 450,
    "isVisible": true,
    "fontStyle": "BOLD",
    "textColor": "#f4f4f5",
    "version": 1,
    "parentId": "gcsf81yb03",
    "tags": [
        "Suggested",
        "Content"
    ],
    "renderMode": "CANVAS",
    "isLoading": false,
    "mobileTopRow": 4,
    "responsiveBehavior": "fill",
    "originalTopRow": 1,
    "borderRadius": "{{appsmith.theme.borderRadius.appBorderRadius}}",
    "mobileLeftColumn": 24,
    "maxDynamicHeight": 9000,
    "originalBottomRow": 20,
    "fontSize": "3rem",
    "minDynamicHeight": 4
}